LICENSE
MANIFEST.in
README.md
setup.py
retry/__init__.py
retry/test.py
retry_on_exceptions.egg-info/PKG-INFO
retry_on_exceptions.egg-info/SOURCES.txt
retry_on_exceptions.egg-info/dependency_links.txt
retry_on_exceptions.egg-info/top_level.txt