Metadata-Version: 1.0
Name: retry-on-exceptions
Version: 0.1
Summary: Decorator for retrying a function N times in case some specified exception occurs. 
Home-page: https://github.com/fjsj/retry_on_exceptions
Author: Flávio Juvenal
Author-email: flaviojuvenal@gmail.com
License: MIT License
Keywords: decorator decorators retry exception
Platform: UNKNOWN
Classifier: Development Status :: 4 - Beta
Classifier: Topic :: Utilities
Classifier: License :: OSI Approved :: MIT License
